kydavra/ANOVASelector.py
kydavra/BregmanDivergenceSelector.py
kydavra/ChiSquaredSelector.py
kydavra/ElasticNet.py
kydavra/FisherSelector.py
kydavra/GeneticAlgorithmSelector.py
kydavra/ICAFilter.py
kydavra/ICAReducer.py
kydavra/ItakuraSaitoSelector.py
kydavra/JensenShannonSelector.py
kydavra/KendallCorrelationSelector.py
kydavra/KullbackLeiblerSelector.py
kydavra/LDAReducer.py
kydavra/LassoSelector.py
kydavra/M3USelector.py
kydavra/MUSESelector.py
kydavra/MixerSelector.py
kydavra/MultiSURFSelector.py
kydavra/PCAFilter.py
kydavra/PCAReducer.py
kydavra/PValueSelector.py
kydavra/PearsonCorrelationSelector.py
kydavra/PhikSelector.py
kydavra/PointBiserialSelector.py
kydavra/ReliefFSelector.py
kydavra/ShannonSelector.py
kydavra/SpearmanCorrelationSelector.py
kydavra/__init__.py
kydavra/errors.py
kydavra-0.3.4.dist-info/LICENSE.txt
kydavra-0.3.4.dist-info/METADATA
kydavra-0.3.4.dist-info/WHEEL
kydavra-0.3.4.dist-info/top_level.txt
kydavra-0.3.4.dist-info/RECORD
