Metadata-Version: 2.1
Name: kydavra
Version: 0.3.4
Summary: Kydavra is a sci-kit learn inspired python library with feature selection methods for Data Science and Macine Learning Model development
Home-page: https://github.com/SigmoidAI/kydavra
Author: SigmoidAI - Păpăluță Vasile, Stojoc Vladimir
Author-email: vladimir.stojoc@gmail.com
License: MIT
Download-URL: https://github.com/ScienceKot/kydavra/archive/v1.0.tar.gz
Keywords: ml,machine learning,feature selection,python
Platform: UNKNOWN
Classifier: Development Status :: 3 - Alpha
Classifier: Framework :: Jupyter
Classifier: Intended Audience :: Science/Research
Classifier: Topic :: Scientific/Engineering :: Artificial Intelligence
Classifier: Topic :: Scientific/Engineering :: Mathematics
Classifier: Topic :: Software Development :: Libraries :: Python Modules
Classifier: Topic :: Software Development :: Build Tools
Classifier: License :: OSI Approved :: MIT License
Classifier: Programming Language :: Python :: 3
Classifier: Programming Language :: Python :: 3.4
Classifier: Programming Language :: Python :: 3.5
Classifier: Programming Language :: Python :: 3.6
Classifier: Programming Language :: Python :: 3.7
Classifier: Programming Language :: Python :: 3.8
License-File: LICENSE.txt
Requires-Dist: numpy
Requires-Dist: pandas
Requires-Dist: scikit-learn
Requires-Dist: statsmodels
Requires-Dist: matplotlib
Requires-Dist: seaborn
